progresspanel/__init__.py
progresspanel/progresspanel.py
progresspanel-0.1.2.dist-info/LICENSE
progresspanel-0.1.2.dist-info/METADATA
progresspanel-0.1.2.dist-info/WHEEL
progresspanel-0.1.2.dist-info/top_level.txt
progresspanel-0.1.2.dist-info/RECORD
