Metadata-Version: 2.1
Name: progresspanel
Version: 0.1.2
Summary: The Progress Panel is a custom tkinter widget that displays a progress bar and buttons (Start/Resume, Pause, Terminate) to control a user-defined task that runs in a separate thread.
Home-page: https://github.com/xuejianma/progresspanel
Author: Xuejian Ma
Author-email: Xuejian.Ma@gmail.com
License: MIT
Keywords: tkinter,progress panel,progress bar,threading,multi thread
License-File: LICENSE
